mendel_plotly_theme/__init__.py
mendel_plotly_theme/theme.py
mendel_plotly_theme-0.1.2.dist-info/LICENSE
mendel_plotly_theme-0.1.2.dist-info/METADATA
mendel_plotly_theme-0.1.2.dist-info/WHEEL
mendel_plotly_theme-0.1.2.dist-info/top_level.txt
mendel_plotly_theme-0.1.2.dist-info/RECORD
