Metadata-Version: 2.1
Name: mendel-plotly-theme
Version: 0.1.2
Summary: A small example package
Author-email: Mendel Engelaer <ante_stamp.0a@icloud.com>
Project-URL: Homepage, https://github.com/Mensel123/mendel-plotly-theme
Classifier: Programming Language :: Python :: 3
Classifier: License :: OSI Approved :: MIT License
Classifier: Operating System :: OS Independent
Requires-Python: >=3.8
License-File: LICENSE
